livingdocs/__init__.py
livingdocs/__main__.py
livingdocs/cli.py
livingdocs/collecting_formatter.py
livingdocs/create_sphinx_feature_file_page.py
livingdocs/create_trace_page.py
livingdocs/create_userneeds_page.py
livingdocs/feature.jinja2
livingdocs/feature_file.py
livingdocs/json_formatter.py
livingdocs/py.typed
livingdocs/scenario.jinja2
livingdocs/template.py
livingdocs/userneeds.jinja2
livingdocs/userneeds.py
livingdocs/userneeds_trace.jinja2
aidee_living_docs-1.0.7.dist-info/METADATA
aidee_living_docs-1.0.7.dist-info/WHEEL
aidee_living_docs-1.0.7.dist-info/entry_points.txt
aidee_living_docs-1.0.7.dist-info/licenses/LICENSE
aidee_living_docs-1.0.7.dist-info/RECORD
