Metadata-Version: 2.4
Name: aidee-living-docs
Version: 1.0.7
Summary: Helpers for generating living documentation with Sphinx and Behave
Project-URL: Homepage, https://github.com/aidee-health/aidee-living-docs
Project-URL: Repository, https://github.com/aidee-health/aidee-living-docs
Project-URL: Changelog, https://github.com/aidee-health/aidee-living-docs/releases
Author-email: Aidee Health AS <hello@aidee.io>
License-Expression: MIT
License-File: LICENSE
Classifier: Development Status :: 5 - Production/Stable
Requires-Python: <4.0,>=3.9
Requires-Dist: behave>=1.2.6
Requires-Dist: jinja2>=3.1.6
